pysfm/__init__.py
pysfm/pysfm.py
pysfm/pysfm_module.py
pysfm/api/__init__.py
pysfm/api/uf_error.py
pysfm/core/HexByteConversion.py
pysfm/core/__init__.py
pysfm/core/command.py
pysfm/core/error.py
pysfm/core/module.py
pysfm/core/packet.py
pysfm/core/pysfm_version.py
pysfm/core/system_parameter.py
pysfm-0.0.161.dist-info/DESCRIPTION.rst
pysfm-0.0.161.dist-info/METADATA
pysfm-0.0.161.dist-info/RECORD
pysfm-0.0.161.dist-info/WHEEL
pysfm-0.0.161.dist-info/metadata.json
pysfm-0.0.161.dist-info/top_level.txt
