Metadata-Version: 2.0
Name: pysfm
Version: 0.0.161
Summary: SFM SDK for python
Home-page: http://sfm.supremainc.com
Author: Brian Lee
Author-email: hclee@suprema.co.kr
License: UNKNOWN
Platform: UNKNOWN
Requires-Dist: pyserial (>=3.4)
